{
  "runId": "run-cc0fa994",
  "workflowId": "wf-lua-vm-finish-final",
  "agent": "worker",
  "task": "Continue implementing, not another narrow contract-cleanup. The user wants the VM completed, not incremental 'passes'. Work from the current tree and the edit plan. Make a substantial semantic implementation push toward the final Lalin-native Lua 5.5 VM: prioritize real runtime behavior over contract/test reshuffling. Focus on completing a connected semantic area end-to-end, especially native-success/Lua-return convergence, protected call/error value routing, closures/upvalues/varargs, numeric/metamethod semantics, table rehash/key semantics, or binary chunk loading. Do not stop after small ABI/test updates. Implement code and tests until you hit a real technical blocker or a substantial completed semantic chunk. Preserve explicit_programming.md, PUC as oracle only, and SponJIT separation. Report concrete semantics implemented, not just passing tests.",
  "cwd": "/home/cedric/dev/lalin",
  "sessionFile": "/home/cedric/dev/lalin/.pi/workflows/.sessions/run-4cd65651.jsonl",
  "status": "completed",
  "created": "2026-05-30T10:57:15.338Z",
  "updated": "2026-05-30T11:08:14.323Z",
  "resumedFromRunId": "run-4cd65651",
  "sessionEntriesBefore": 96,
  "exitCode": 0,
  "stopReason": "stop",
  "lastOutputPreview": "## Completed\n\nImplemented a substantial connected runtime push in two areas:\n\n1. **Native success now converges with Lua return/resume**\n   - `call_native` no longer treats `NativeResult.OK` as a gated/stub outcome.\n   - Native results are adjusted through `resume_after_return` using the explicit `NativeCallContext.resume`.\n   - `vm_loop.native_ret` now reloads the active frame’s `code/constants` and resumes execution, matching the frame-cache invariant used by Lua returns.\n   - Added an end-to-",
  "sessionEntriesAfter": 189
}
